leave/__init__.py
leave/admin.py
leave/apps.py
leave/forms.py
leave/models.py
leave/signals.py
leave/tests.py
leave/urls.py
leave/urls_report.py
leave/utils.py
leave/utils_2.py
leave/views.py
leave/api/urls.py
leave/api/views.py
leave/api/__pycache__/urls.cpython-310.pyc
leave/api/__pycache__/views.cpython-310.pyc
leave/migrations/0001_initial.py
leave/migrations/0002_remove_taskdelegate_date.py
leave/migrations/0003_rename_taskdelegate_leavedelegate.py
leave/migrations/0004_alter_leavedelegate_employee.py
leave/migrations/0005_rename_is_approve_leavedelegate_is_confirm.py
leave/migrations/0006_leavedelegate_is_confirm2.py
leave/migrations/0007_leavetype_total.py
leave/migrations/0008_rename_de_confirm_leave_de_approve_and_more.py
leave/migrations/0009_rename_is_lock_leave_s_is_finish_and_more.py
leave/migrations/0010_leave_de_obs_leave_hr_obs_leave_unit_obs.py
leave/migrations/0011_remove_leave_de_obs_remove_leave_hr_obs_and_more.py
leave/migrations/0012_alter_leavedelegate_leave_alter_leaveunit_leave.py
leave/migrations/0013_leave_is_finish.py
leave/migrations/0014_leavehr_leavede.py
leave/migrations/0015_alter_leavede_obs_alter_leavedelegate_obs_and_more.py
leave/migrations/0016_leave_is_print.py
leave/migrations/0017_remove_leavecount_datetime_remove_leavecount_hashed_and_more.py
leave/migrations/0018_alter_leavecount_balance.py
leave/migrations/0019_leave_s_is_delegate.py
leave/migrations/0020_remove_leave_s_is_delegate.py
leave/migrations/0021_leave_is_approve_leave_is_reject.py
leave/migrations/0022_rename_s_is_finish_leave_is_delegate_and_more.py
leave/migrations/0023_remove_leavedelegate_is_send.py
leave/migrations/0024_alter_leave_is_active.py
leave/migrations/0025_auto_20221210_2329.py
leave/migrations/0026_auto_20221210_2356.py
leave/migrations/0027_auto_20221211_0022.py
leave/migrations/0028_auto_20221211_0202.py
leave/migrations/0029_leavedep.py
leave/migrations/0030_auto_20221211_1206.py
leave/migrations/0031_leave_is_update.py
django_ipghrms_leave-1.20.dist-info/LICENSE
django_ipghrms_leave-1.20.dist-info/METADATA
django_ipghrms_leave-1.20.dist-info/WHEEL
django_ipghrms_leave-1.20.dist-info/top_level.txt
django_ipghrms_leave-1.20.dist-info/RECORD
